drawtable/__init__.py
drawtable/styles.py
drawtable/csvless/__init__.py
drawtable/csvless/__main__.py
drawtable/csvless/getenv.py
drawtable-0.2.0.dist-info/METADATA
drawtable-0.2.0.dist-info/RECORD
drawtable-0.2.0.dist-info/WHEEL
drawtable-0.2.0.dist-info/entry_points.txt
drawtable-0.2.0.dist-info/top_level.txt
